[{
  "id": 1,
  "slug": "/lorem/ipsum.html",
  "title": "Sapien arcu sed augue",
  "city": "Livramento",
  "venue": "Redhold Gallery",
  "year": 1964,
  "solo": true,
  "images": [
    {
      "width": 571,
      "height": 886,
      "alt": "Ipsum dolor sit amet consectetuer adipiscing",
      "title": "Eros viverra eget congue eget semper"
    },
    {
      "width": 855,
      "height": 587,
      "alt": "Sed sagittis nam congue risus",
      "title": "Est quam pharetra"
    },
    {
      "width": 806,
      "height": 569,
      "alt": "Mauris non ligula pellentesque",
      "title": "Parturient montes nascetur ridiculus mus"
    },
    {
      "width": 634,
      "height": 734,
      "alt": "Leo odio condimentum id luctus",
      "title": "Blandit non interdum"
    }
  ]
}, {
  "id": 2,
  "slug": "/erat/id/mauris/vulputate/elementum/nullam/varius.jpg",
  "title": "Mi integer ac neque duis bibendum morbi non",
  "city": "Marsh Harbour",
  "venue": "Greenlam Gallery",
  "year": 1987,
  "solo": true,
  "images": [
    {
      "width": 950,
      "height": 954,
      "alt": "Porttitor lorem id ligula",
      "title": "Ac leo pellentesque ultrices"
    },
    {
      "width": 844,
      "height": 636,
      "alt": "Et ultrices posuere",
      "title": "Dis parturient montes"
    },
    {
      "width": 875,
      "height": 980,
      "alt": "Interdum in ante",
      "title": "Dictumst etiam faucibus cursus urna ut tellus nulla"
    },
    {
      "width": 714,
      "height": 860,
      "alt": "Ac enim in",
      "title": "Felis eu sapien cursus"
    }
  ]
}, {
  "id": 3,
  "slug": "/dapibus/nulla/suscipit/ligula/in.html",
  "title": "Nulla tellus in sagittis dui vel nisl",
  "city": "Liuzuo",
  "venue": "It Gallery",
  "year": 1978,
  "solo": false,
  "images": [
    {
      "width": 612,
      "height": 527,
      "alt": "Quis odio consequat varius integer ac leo pellentesque",
      "title": "Nec nisi vulputate nonummy"
    }
  ]
}, {
  "id": 4,
  "slug": "/dui/proin/leo/odio/porttitor/id/consequat.aspx",
  "title": "Montes nascetur ridiculus mus",
  "city": "Wailiang",
  "venue": "Sub-Ex Gallery",
  "year": 1963,
  "solo": false,
  "images": [
    {
      "width": 876,
      "height": 987,
      "alt": "Quam a odio in hac habitasse platea dictumst",
      "title": "Semper sapien a libero nam dui"
    },
    {
      "width": 591,
      "height": 790,
      "alt": "Orci luctus et ultrices posuere cubilia curae donec",
      "title": "Nisl duis ac nibh fusce lacus purus aliquet"
    },
    {
      "width": 724,
      "height": 904,
      "alt": "Ligula vehicula consequat morbi a ipsum integer a",
      "title": "Eget elit sodales scelerisque"
    },
    {
      "width": 800,
      "height": 692,
      "alt": "Aliquam convallis nunc proin at",
      "title": "Sed lacus morbi sem mauris laoreet ut rhoncus"
    },
    {
      "width": 782,
      "height": 602,
      "alt": "At nulla suspendisse potenti",
      "title": "Ultrices aliquet maecenas leo odio condimentum id"
    }
  ]
}, {
  "id": 5,
  "slug": "/luctus/tincidunt/nulla/mollis/molestie.js",
  "title": "Lectus in quam fringilla rhoncus",
  "city": "Chicago",
  "venue": "Bytecard Gallery",
  "year": 2008,
  "solo": true,
  "images": [
    {
      "width": 614,
      "height": 978,
      "alt": "Ante vestibulum ante ipsum primis",
      "title": "Ac nulla sed vel enim sit amet"
    },
    {
      "width": 683,
      "height": 567,
      "alt": "Sapien placerat ante nulla",
      "title": "Vitae mattis nibh ligula"
    }
  ]
}, {
  "id": 6,
  "slug": "/sit/amet/eros/suspendisse/accumsan/tortor.aspx",
  "title": "Nulla tellus in sagittis dui vel nisl duis",
  "city": "Liangwangzhuang",
  "venue": "Zathin Gallery",
  "year": 1987,
  "solo": false,
  "images": [
    {
      "width": 758,
      "height": 745,
      "alt": "Porttitor lacus at",
      "title": "Consectetuer eget rutrum at lorem integer tincidunt ante"
    }
  ]
}, {
  "id": 7,
  "slug": "/justo.html",
  "title": "Leo maecenas pulvinar lobortis est phasellus",
  "city": "Petare",
  "venue": "Zamit Gallery",
  "year": 1964,
  "solo": true,
  "images": [
    {
      "width": 607,
      "height": 522,
      "alt": "Suspendisse potenti cras in purus eu",
      "title": "Aliquet maecenas leo"
    },
    {
      "width": 516,
      "height": 562,
      "alt": "Cum sociis natoque penatibus et",
      "title": "Justo eu massa"
    },
    {
      "width": 551,
      "height": 880,
      "alt": "Adipiscing elit proin risus praesent lectus vestibulum quam",
      "title": "Sed vel enim sit amet nunc viverra"
    }
  ]
}, {
  "id": 8,
  "slug": "/rutrum/rutrum/neque/aenean.png",
  "title": "Facilisi cras non velit",
  "city": "Nguigmi",
  "venue": "Stim Gallery",
  "year": 1979,
  "solo": true,
  "images": [
    {
      "width": 669,
      "height": 519,
      "alt": "Sapien non mi integer ac",
      "title": "Congue diam id ornare imperdiet"
    },
    {
      "width": 813,
      "height": 808,
      "alt": "Luctus cum sociis natoque penatibus et magnis dis",
      "title": "Sapien varius ut blandit non interdum in ante"
    },
    {
      "width": 800,
      "height": 835,
      "alt": "Ultrices posuere cubilia curae duis faucibus accumsan",
      "title": "Est lacinia nisi venenatis tristique fusce congue diam"
    },
    {
      "width": 915,
      "height": 737,
      "alt": "Amet lobortis sapien sapien non mi integer ac",
      "title": "Vulputate ut ultrices vel augue vestibulum"
    }
  ]
}, {
  "id": 9,
  "slug": "/augue/vel/accumsan/tellus/nisi.aspx",
  "title": "Porta volutpat quam pede lobortis ligula",
  "city": "Malianchuan",
  "venue": "Voltsillam Gallery",
  "year": 1988,
  "solo": true,
  "images": [
    {
      "width": 603,
      "height": 607,
      "alt": "Libero nam dui proin leo",
      "title": "Ut blandit non interdum in"
    },
    {
      "width": 508,
      "height": 997,
      "alt": "Nibh quisque id justo sit amet sapien",
      "title": "Libero quis orci"
    },
    {
      "width": 848,
      "height": 828,
      "alt": "Consequat ut nulla sed",
      "title": "Volutpat eleifend donec ut"
    },
    {
      "width": 680,
      "height": 842,
      "alt": "Praesent lectus vestibulum quam sapien varius ut",
      "title": "Sem sed sagittis nam congue risus"
    }
  ]
}, {
  "id": 10,
  "slug": "/morbi/odio/odio/elementum/eu/interdum.jpg",
  "title": "Sit amet justo morbi",
  "city": "Hufang",
  "venue": "Konklux Gallery",
  "year": 1997,
  "solo": false,
  "images": [
    {
      "width": 960,
      "height": 998,
      "alt": "Vel lectus in quam",
      "title": "Velit vivamus vel nulla eget eros elementum"
    },
    {
      "width": 767,
      "height": 725,
      "alt": "Porta volutpat erat quisque erat eros viverra eget",
      "title": "Id nisl venenatis lacinia aenean sit amet justo"
    },
    {
      "width": 845,
      "height": 825,
      "alt": "Non lectus aliquam sit amet diam",
      "title": "Dolor morbi vel lectus"
    },
    {
      "width": 534,
      "height": 511,
      "alt": "Posuere felis sed lacus morbi sem",
      "title": "Gravida nisi at"
    },
    {
      "width": 880,
      "height": 712,
      "alt": "Volutpat sapien arcu sed augue",
      "title": "Mattis odio donec vitae"
    }
  ]
}, {
  "id": 11,
  "slug": "/fermentum.aspx",
  "title": "Non mattis pulvinar nulla pede ullamcorper augue",
  "city": "Dois Portos",
  "venue": "Gembucket Gallery",
  "year": 1971,
  "solo": false,
  "images": [
    {
      "width": 713,
      "height": 692,
      "alt": "Id mauris vulputate elementum nullam",
      "title": "Purus sit amet nulla quisque arcu libero"
    }
  ]
}, {
  "id": 12,
  "slug": "/quis/orci/eget/orci/vehicula/condimentum.js",
  "title": "Magnis dis parturient montes nascetur ridiculus mus vivamus",
  "city": "Jiangkou",
  "venue": "Flexidy Gallery",
  "year": 1985,
  "solo": false,
  "images": [
    {
      "width": 835,
      "height": 747,
      "alt": "Eu tincidunt in",
      "title": "Ac est lacinia nisi"
    }
  ]
}, {
  "id": 13,
  "slug": "/primis/in/faucibus.jpg",
  "title": "Tellus in sagittis dui vel nisl",
  "city": "Špišić-Bukovica",
  "venue": "Zamit Gallery",
  "year": 1997,
  "solo": false,
  "images": [
    {
      "width": 800,
      "height": 736,
      "alt": "Quam sollicitudin vitae consectetuer",
      "title": "Ut nulla sed accumsan felis"
    },
    {
      "width": 886,
      "height": 532,
      "alt": "Vestibulum eget vulputate ut ultrices vel",
      "title": "Ac tellus semper interdum mauris ullamcorper purus"
    }
  ]
}, {
  "id": 14,
  "slug": "/ligula/vehicula/consequat/morbi/a.js",
  "title": "Sollicitudin ut suscipit",
  "city": "Ungus-Ungus",
  "venue": "Vagram Gallery",
  "year": 1981,
  "solo": true,
  "images": [
    {
      "width": 990,
      "height": 716,
      "alt": "Sagittis dui vel nisl",
      "title": "Ipsum primis in faucibus orci"
    },
    {
      "width": 585,
      "height": 851,
      "alt": "Aliquet maecenas leo odio",
      "title": "Rutrum rutrum neque aenean auctor gravida sem"
    },
    {
      "width": 891,
      "height": 870,
      "alt": "Quis turpis sed ante vivamus",
      "title": "Nulla pede ullamcorper augue a"
    }
  ]
}, {
  "id": 15,
  "slug": "/non.js",
  "title": "Ut volutpat sapien arcu",
  "city": "Sugiharjo",
  "venue": "Otcom Gallery",
  "year": 1988,
  "solo": false,
  "images": [
    {
      "width": 846,
      "height": 999,
      "alt": "In faucibus orci luctus et ultrices posuere",
      "title": "Nullam orci pede venenatis non sodales sed tincidunt"
    },
    {
      "width": 784,
      "height": 816,
      "alt": "Integer a nibh in quis justo maecenas",
      "title": "Sem fusce consequat nulla nisl nunc nisl duis"
    },
    {
      "width": 807,
      "height": 534,
      "alt": "Pede ullamcorper augue a suscipit nulla",
      "title": "Rhoncus mauris enim leo rhoncus sed"
    },
    {
      "width": 977,
      "height": 758,
      "alt": "Velit donec diam neque vestibulum",
      "title": "In consequat ut nulla sed accumsan felis ut"
    },
    {
      "width": 757,
      "height": 568,
      "alt": "Mollis molestie lorem quisque ut erat",
      "title": "Pede venenatis non sodales sed"
    }
  ]
}, {
  "id": 16,
  "slug": "/consequat/in/consequat/ut.xml",
  "title": "Bibendum felis sed interdum venenatis turpis enim",
  "city": "Alaghsas",
  "venue": "Ronstring Gallery",
  "year": 1998,
  "solo": true,
  "images": [
    {
      "width": 828,
      "height": 646,
      "alt": "Orci nullam molestie nibh in lectus",
      "title": "Erat vestibulum sed magna at nunc commodo"
    },
    {
      "width": 707,
      "height": 788,
      "alt": "Aliquet maecenas leo odio condimentum",
      "title": "Dignissim vestibulum vestibulum ante ipsum"
    },
    {
      "width": 885,
      "height": 783,
      "alt": "Cras in purus eu magna vulputate",
      "title": "Semper est quam pharetra magna ac"
    },
    {
      "width": 547,
      "height": 763,
      "alt": "Placerat praesent blandit nam",
      "title": "Nisl nunc nisl duis bibendum"
    },
    {
      "width": 795,
      "height": 952,
      "alt": "Aliquam augue quam sollicitudin vitae",
      "title": "Diam nam tristique tortor eu"
    }
  ]
}, {
  "id": 17,
  "slug": "/quam/nec/dui/luctus/rutrum.json",
  "title": "Mauris lacinia sapien quis libero nullam",
  "city": "Laocheng",
  "venue": "Bytecard Gallery",
  "year": 1999,
  "solo": false,
  "images": [
    {
      "width": 698,
      "height": 635,
      "alt": "Lorem vitae mattis nibh ligula",
      "title": "In eleifend quam a odio in"
    },
    {
      "width": 514,
      "height": 629,
      "alt": "Justo sollicitudin ut suscipit a feugiat et",
      "title": "A libero nam"
    }
  ]
}, {
  "id": 18,
  "slug": "/erat.html",
  "title": "Eu sapien cursus vestibulum proin",
  "city": "Quintães",
  "venue": "Tres-Zap Gallery",
  "year": 1973,
  "solo": false,
  "images": [
    {
      "width": 997,
      "height": 703,
      "alt": "Odio porttitor id consequat",
      "title": "Nonummy maecenas tincidunt lacus at velit vivamus"
    }
  ]
}, {
  "id": 19,
  "slug": "/at/nunc/commodo/placerat.html",
  "title": "A nibh in quis justo maecenas rhoncus aliquam",
  "city": "Lincoln",
  "venue": "Stim Gallery",
  "year": 1987,
  "solo": true,
  "images": [
    {
      "width": 1000,
      "height": 996,
      "alt": "Bibendum felis sed interdum venenatis turpis",
      "title": "Odio consequat varius integer ac"
    },
    {
      "width": 964,
      "height": 832,
      "alt": "Nunc nisl duis bibendum felis sed interdum venenatis",
      "title": "Magna vulputate luctus cum sociis natoque penatibus et"
    },
    {
      "width": 847,
      "height": 629,
      "alt": "Feugiat non pretium quis",
      "title": "Eleifend donec ut"
    },
    {
      "width": 809,
      "height": 751,
      "alt": "Ultrices libero non mattis pulvinar nulla pede ullamcorper",
      "title": "Nulla ultrices aliquet maecenas leo odio condimentum id"
    },
    {
      "width": 983,
      "height": 934,
      "alt": "Platea dictumst etiam faucibus cursus",
      "title": "Volutpat quam pede lobortis ligula sit"
    }
  ]
}, {
  "id": 20,
  "slug": "/et.json",
  "title": "Nulla nunc purus phasellus",
  "city": "Marquard",
  "venue": "Bitchip Gallery",
  "year": 1965,
  "solo": true,
  "images": [
    {
      "width": 832,
      "height": 777,
      "alt": "Odio elementum eu interdum eu",
      "title": "Adipiscing elit proin interdum mauris non ligula pellentesque"
    }
  ]
}, {
  "id": 21,
  "slug": "/adipiscing/elit/proin.aspx",
  "title": "Metus sapien ut nunc vestibulum ante",
  "city": "Louisville",
  "venue": "Lotstring Gallery",
  "year": 1967,
  "solo": false,
  "images": [
    {
      "width": 940,
      "height": 946,
      "alt": "Ultrices enim lorem ipsum dolor sit amet consectetuer",
      "title": "Scelerisque quam turpis adipiscing lorem vitae"
    }
  ]
}, {
  "id": 22,
  "slug": "/maecenas/tristique.html",
  "title": "Non mi integer ac neque duis bibendum morbi",
  "city": "Espargos",
  "venue": "Latlux Gallery",
  "year": 2007,
  "solo": true,
  "images": [
    {
      "width": 726,
      "height": 579,
      "alt": "Nulla tempus vivamus",
      "title": "Vehicula condimentum curabitur in libero ut massa"
    },
    {
      "width": 651,
      "height": 633,
      "alt": "Praesent id massa id nisl venenatis lacinia aenean",
      "title": "Odio curabitur convallis duis consequat"
    },
    {
      "width": 814,
      "height": 525,
      "alt": "Nulla tempus vivamus in felis",
      "title": "Nibh ligula nec sem duis aliquam convallis nunc"
    },
    {
      "width": 735,
      "height": 863,
      "alt": "In hac habitasse platea dictumst",
      "title": "Sodales sed tincidunt"
    },
    {
      "width": 898,
      "height": 659,
      "alt": "Luctus et ultrices posuere cubilia curae nulla dapibus",
      "title": "Id nisl venenatis"
    }
  ]
}, {
  "id": 23,
  "slug": "/diam/cras/pellentesque/volutpat/dui/maecenas.js",
  "title": "Luctus et ultrices posuere cubilia",
  "city": "Kitob",
  "venue": "Tampflex Gallery",
  "year": 1971,
  "solo": false,
  "images": [
    {
      "width": 591,
      "height": 893,
      "alt": "Donec semper sapien a libero nam dui",
      "title": "Aliquam convallis nunc proin at turpis a"
    },
    {
      "width": 879,
      "height": 760,
      "alt": "Nulla sed accumsan",
      "title": "A nibh in quis justo"
    },
    {
      "width": 715,
      "height": 714,
      "alt": "In felis donec semper sapien a libero",
      "title": "Sollicitudin mi sit amet lobortis"
    },
    {
      "width": 546,
      "height": 980,
      "alt": "Mollis molestie lorem quisque ut erat",
      "title": "In tempor turpis nec euismod scelerisque quam"
    },
    {
      "width": 843,
      "height": 947,
      "alt": "Nulla sed vel enim sit",
      "title": "Nullam porttitor lacus at turpis donec"
    }
  ]
}, {
  "id": 24,
  "slug": "/sodales/sed/tincidunt/eu.xml",
  "title": "Mauris enim leo rhoncus sed vestibulum sit amet",
  "city": "Tamisan",
  "venue": "Bitchip Gallery",
  "year": 1991,
  "solo": true,
  "images": [
    {
      "width": 967,
      "height": 700,
      "alt": "Est risus auctor sed",
      "title": "Sit amet sem"
    },
    {
      "width": 694,
      "height": 821,
      "alt": "Nibh quisque id justo sit",
      "title": "Sapien non mi"
    }
  ]
}, {
  "id": 25,
  "slug": "/eget/semper/rutrum/nulla/nunc/purus/phasellus.jpg",
  "title": "Ac consequat metus sapien",
  "city": "Fenggao",
  "venue": "Temp Gallery",
  "year": 1970,
  "solo": false,
  "images": [
    {
      "width": 947,
      "height": 713,
      "alt": "Natoque penatibus et magnis",
      "title": "Proin risus praesent lectus vestibulum"
    },
    {
      "width": 650,
      "height": 558,
      "alt": "Phasellus id sapien in sapien iaculis",
      "title": "Id nulla ultrices aliquet"
    },
    {
      "width": 549,
      "height": 503,
      "alt": "Augue vel accumsan",
      "title": "Curae nulla dapibus dolor vel est"
    },
    {
      "width": 560,
      "height": 898,
      "alt": "Suscipit ligula in lacus curabitur at ipsum",
      "title": "Lectus aliquam sit amet diam"
    },
    {
      "width": 707,
      "height": 966,
      "alt": "Ante ipsum primis in faucibus orci luctus",
      "title": "Sit amet nulla quisque arcu libero"
    }
  ]
}, {
  "id": 26,
  "slug": "/etiam.png",
  "title": "Cras pellentesque volutpat dui",
  "city": "Shipaidong",
  "venue": "Cardify Gallery",
  "year": 2002,
  "solo": false,
  "images": [
    {
      "width": 751,
      "height": 545,
      "alt": "Pellentesque viverra pede ac",
      "title": "Id massa id"
    }
  ]
}, {
  "id": 27,
  "slug": "/donec/diam/neque/vestibulum/eget.aspx",
  "title": "Donec diam neque vestibulum",
  "city": "Anhua Daying",
  "venue": "Zathin Gallery",
  "year": 1998,
  "solo": false,
  "images": [
    {
      "width": 530,
      "height": 632,
      "alt": "Tincidunt ante vel ipsum praesent blandit lacinia",
      "title": "Vestibulum eget vulputate ut"
    },
    {
      "width": 900,
      "height": 601,
      "alt": "Vestibulum aliquet ultrices erat tortor",
      "title": "In est risus auctor"
    },
    {
      "width": 540,
      "height": 754,
      "alt": "Potenti in eleifend quam a odio in hac",
      "title": "Nisl duis bibendum felis"
    },
    {
      "width": 553,
      "height": 723,
      "alt": "In hac habitasse platea dictumst aliquam augue quam",
      "title": "Lobortis sapien sapien non mi integer"
    },
    {
      "width": 884,
      "height": 776,
      "alt": "Nulla ut erat id mauris vulputate elementum nullam",
      "title": "Eu est congue elementum in"
    }
  ]
}, {
  "id": 28,
  "slug": "/curabitur/gravida/nisi.html",
  "title": "In congue etiam justo",
  "city": "Tando Jām",
  "venue": "Zathin Gallery",
  "year": 1988,
  "solo": true,
  "images": [
    {
      "width": 708,
      "height": 861,
      "alt": "Sapien quis libero",
      "title": "Est lacinia nisi venenatis tristique fusce congue diam"
    },
    {
      "width": 910,
      "height": 725,
      "alt": "Sit amet turpis",
      "title": "Viverra eget congue"
    }
  ]
}, {
  "id": 29,
  "slug": "/volutpat/eleifend.js",
  "title": "Sed accumsan felis ut at dolor",
  "city": "Alto de la Estancia",
  "venue": "Asoka Gallery",
  "year": 1975,
  "solo": true,
  "images": [
    {
      "width": 600,
      "height": 739,
      "alt": "Rutrum rutrum neque",
      "title": "Nullam orci pede venenatis non"
    },
    {
      "width": 694,
      "height": 799,
      "alt": "Accumsan tortor quis turpis sed",
      "title": "Venenatis lacinia aenean sit amet justo morbi ut"
    },
    {
      "width": 613,
      "height": 576,
      "alt": "Felis ut at dolor quis odio consequat varius",
      "title": "Convallis tortor risus dapibus"
    },
    {
      "width": 966,
      "height": 660,
      "alt": "Eu sapien cursus vestibulum proin eu mi nulla",
      "title": "Iaculis justo in hac habitasse"
    },
    {
      "width": 960,
      "height": 830,
      "alt": "Tortor duis mattis egestas metus aenean fermentum donec",
      "title": "In faucibus orci luctus"
    }
  ]
}, {
  "id": 30,
  "slug": "/nulla.jpg",
  "title": "Mi pede malesuada in imperdiet et commodo",
  "city": "Huifa",
  "venue": "Vagram Gallery",
  "year": 1989,
  "solo": false,
  "images": [
    {
      "width": 735,
      "height": 852,
      "alt": "Primis in faucibus",
      "title": "Sagittis dui vel nisl duis ac"
    },
    {
      "width": 681,
      "height": 942,
      "alt": "Amet eros suspendisse accumsan tortor",
      "title": "Orci luctus et ultrices posuere cubilia"
    },
    {
      "width": 676,
      "height": 751,
      "alt": "Vivamus in felis eu",
      "title": "Diam nam tristique"
    },
    {
      "width": 883,
      "height": 662,
      "alt": "Enim lorem ipsum dolor sit amet consectetuer",
      "title": "In felis eu sapien cursus vestibulum"
    }
  ]
}, {
  "id": 31,
  "slug": "/ipsum/dolor/sit/amet.json",
  "title": "Odio justo sollicitudin ut suscipit a feugiat et",
  "city": "Río Viejo",
  "venue": "Zamit Gallery",
  "year": 2004,
  "solo": true,
  "images": [
    {
      "width": 932,
      "height": 800,
      "alt": "Ante ipsum primis",
      "title": "Semper rutrum nulla nunc purus"
    }
  ]
}, {
  "id": 32,
  "slug": "/erat/curabitur/gravida/nisi/at/nibh.png",
  "title": "Integer ac neque duis bibendum morbi non quam",
  "city": "Renyi",
  "venue": "Sonsing Gallery",
  "year": 1992,
  "solo": false,
  "images": [
    {
      "width": 839,
      "height": 906,
      "alt": "Id pretium iaculis diam erat fermentum justo nec",
      "title": "Maecenas ut massa quis"
    }
  ]
}, {
  "id": 33,
  "slug": "/diam/in/magna/bibendum/imperdiet/nullam/orci.aspx",
  "title": "Cursus vestibulum proin eu mi nulla",
  "city": "Gniechowice",
  "venue": "Bigtax Gallery",
  "year": 2006,
  "solo": false,
  "images": [
    {
      "width": 878,
      "height": 540,
      "alt": "Hac habitasse platea dictumst maecenas ut massa quis",
      "title": "Curae nulla dapibus dolor vel est"
    }
  ]
}, {
  "id": 34,
  "slug": "/non/mi/integer/ac.json",
  "title": "Rhoncus aliquet pulvinar sed",
  "city": "Vale de São Cosme",
  "venue": "Asoka Gallery",
  "year": 1988,
  "solo": true,
  "images": [
    {
      "width": 586,
      "height": 864,
      "alt": "Eleifend quam a odio",
      "title": "Ultrices posuere cubilia curae mauris viverra"
    },
    {
      "width": 727,
      "height": 709,
      "alt": "Ut mauris eget massa tempor convallis nulla",
      "title": "Metus sapien ut nunc"
    },
    {
      "width": 801,
      "height": 934,
      "alt": "Mus vivamus vestibulum sagittis sapien cum",
      "title": "Suscipit nulla elit ac nulla sed vel"
    },
    {
      "width": 565,
      "height": 997,
      "alt": "A nibh in quis justo maecenas",
      "title": "Et eros vestibulum ac"
    },
    {
      "width": 582,
      "height": 942,
      "alt": "Gravida sem praesent id",
      "title": "Rutrum at lorem integer tincidunt"
    }
  ]
}, {
  "id": 35,
  "slug": "/ut/massa/quis/augue/luctus/tincidunt.jpg",
  "title": "Nullam porttitor lacus at",
  "city": "Xincun",
  "venue": "Transcof Gallery",
  "year": 2002,
  "solo": false,
  "images": [
    {
      "width": 801,
      "height": 977,
      "alt": "Ut nulla sed",
      "title": "Tincidunt in leo maecenas pulvinar lobortis est phasellus"
    },
    {
      "width": 784,
      "height": 864,
      "alt": "Massa tempor convallis nulla neque libero convallis eget",
      "title": "Faucibus orci luctus et"
    },
    {
      "width": 755,
      "height": 525,
      "alt": "Ipsum primis in faucibus orci luctus",
      "title": "Integer ac neque duis bibendum morbi non"
    }
  ]
}, {
  "id": 36,
  "slug": "/elit/sodales/scelerisque/mauris.jsp",
  "title": "Lectus aliquam sit amet diam in",
  "city": "Dagsar",
  "venue": "Otcom Gallery",
  "year": 1975,
  "solo": true,
  "images": [
    {
      "width": 626,
      "height": 755,
      "alt": "Quis augue luctus tincidunt nulla mollis",
      "title": "In faucibus orci"
    },
    {
      "width": 543,
      "height": 831,
      "alt": "Lobortis sapien sapien",
      "title": "Sagittis dui vel nisl duis ac"
    },
    {
      "width": 736,
      "height": 688,
      "alt": "Sapien a libero nam dui proin",
      "title": "Pede justo lacinia eget tincidunt eget tempus vel"
    },
    {
      "width": 782,
      "height": 763,
      "alt": "Quis odio consequat varius integer ac",
      "title": "Tristique in tempus sit amet sem"
    }
  ]
}, {
  "id": 37,
  "slug": "/elementum/eu/interdum/eu/tincidunt/in/leo.aspx",
  "title": "Interdum mauris ullamcorper purus sit amet",
  "city": "Palangkaraya",
  "venue": "Tempsoft Gallery",
  "year": 2008,
  "solo": false,
  "images": [
    {
      "width": 606,
      "height": 668,
      "alt": "Magna vestibulum aliquet ultrices erat tortor sollicitudin",
      "title": "Ac tellus semper interdum mauris ullamcorper purus sit"
    },
    {
      "width": 642,
      "height": 716,
      "alt": "Vitae mattis nibh ligula nec sem duis aliquam",
      "title": "Mauris ullamcorper purus sit amet nulla quisque"
    },
    {
      "width": 728,
      "height": 649,
      "alt": "Faucibus cursus urna ut tellus nulla ut erat",
      "title": "Congue elementum in"
    },
    {
      "width": 961,
      "height": 888,
      "alt": "Orci eget orci vehicula condimentum curabitur",
      "title": "Ipsum ac tellus semper interdum mauris"
    },
    {
      "width": 619,
      "height": 955,
      "alt": "Erat fermentum justo",
      "title": "Cras mi pede malesuada"
    }
  ]
}, {
  "id": 38,
  "slug": "/dictumst/etiam/faucibus.aspx",
  "title": "Lorem integer tincidunt ante vel ipsum praesent blandit",
  "city": "Rochester",
  "venue": "Job Gallery",
  "year": 1965,
  "solo": true,
  "images": [
    {
      "width": 703,
      "height": 644,
      "alt": "Magna at nunc commodo placerat praesent blandit nam",
      "title": "Augue vestibulum rutrum rutrum neque aenean auctor"
    },
    {
      "width": 549,
      "height": 869,
      "alt": "Nisi vulputate nonummy maecenas tincidunt lacus at",
      "title": "Odio cras mi pede malesuada in"
    },
    {
      "width": 871,
      "height": 976,
      "alt": "Felis sed interdum venenatis",
      "title": "Proin eu mi nulla ac enim in"
    },
    {
      "width": 579,
      "height": 616,
      "alt": "Aliquam sit amet diam in",
      "title": "Libero non mattis pulvinar nulla pede"
    }
  ]
}, {
  "id": 39,
  "slug": "/consequat/dui/nec/nisi/volutpat/eleifend/donec.html",
  "title": "Libero non mattis pulvinar nulla pede",
  "city": "Argotirto Krajan",
  "venue": "Prodder Gallery",
  "year": 1977,
  "solo": false,
  "images": [
    {
      "width": 678,
      "height": 717,
      "alt": "Sit amet sem fusce consequat nulla",
      "title": "In blandit ultrices enim lorem ipsum dolor"
    },
    {
      "width": 935,
      "height": 877,
      "alt": "Eget massa tempor convallis nulla neque",
      "title": "Quis lectus suspendisse potenti in eleifend quam a"
    },
    {
      "width": 664,
      "height": 785,
      "alt": "Magnis dis parturient montes nascetur ridiculus",
      "title": "Cras in purus eu magna vulputate"
    }
  ]
}, {
  "id": 40,
  "slug": "/nulla/justo/aliquam/quis/turpis/eget/elit.aspx",
  "title": "Etiam vel augue",
  "city": "Yangchengzhuang",
  "venue": "Y-Solowarm Gallery",
  "year": 1982,
  "solo": false,
  "images": [
    {
      "width": 715,
      "height": 562,
      "alt": "Massa id nisl venenatis lacinia aenean",
      "title": "Enim leo rhoncus"
    },
    {
      "width": 632,
      "height": 832,
      "alt": "In sagittis dui vel nisl duis ac",
      "title": "Odio elementum eu"
    },
    {
      "width": 582,
      "height": 896,
      "alt": "Quis odio consequat varius integer",
      "title": "Dolor sit amet"
    }
  ]
}]
